pincode/__init__.py
pincode/regex.txt
pincode-3.0.0.dist-info/WHEEL
pincode-3.0.0.dist-info/METADATA
pincode-3.0.0.dist-info/licenses/LICENSE
pincode-3.0.0.dist-info/RECORD
