Metadata-Version: 2.1
Name: pincode
Version: 3.0.0
Summary: A simple offline pincode validator for India
License: MIT
Keywords: pincode,regex,offline,pin,validator
Author-email: Nemo <python@captnemo.in>
Requires-Python: >=3.9
Classifier: Development Status :: 4 - Beta
Classifier: Intended Audience :: Developers
Classifier: Topic :: Software Development :: Libraries
Provides-Extra: dev
Requires-Dist: nose2; extra == "dev"
Project-URL: Documentation, https://github.com/captn3m0/india-pincode-regex/wiki
Project-URL: Repository, https://github.com/captn3m0/india-pincode-regex
Project-URL: homepage, https://github.com/captn3m0/india-pincode-regex
